PPool/Pool.py
PPool/__init__.py
PPool-1.0.0.dist-info/METADATA
PPool-1.0.0.dist-info/RECORD
PPool-1.0.0.dist-info/WHEEL
PPool-1.0.0.dist-info/top_level.txt
