Metadata-Version: 2.1
Name: PPool
Version: 1.0.0
Summary: A Pool for Processes in Python with locks
Home-page: https://github.com/oeg-upm/PPool
Author: Ahmad Alobaid
Author-email: aalobaid@fi.upm.es
License: UNKNOWN
Platform: UNKNOWN
Classifier: Programming Language :: Python :: 2
Classifier: License :: OSI Approved :: Apache Software License
Classifier: Operating System :: OS Independent
Classifier: Topic :: System :: Operating System
